maker/BestFVGStrategyMaker.py
maker/BestTopDownStrategyMaker.py
maker/LiquidityGrabStrategyMaker.py
maker/MACDStrategyMaker.py
maker/SMCStrategyMaker.py
maker/StrategyMaker.py
maker/TargetValidationEngine.py
maker/ThreeLineStrategyMaker.py
maker/__init__.py
maker/ai_validation/__init__.py
maker/ai_validation/ai_client.py
maker/ai_validation/analytics.py
maker/ai_validation/config.py
maker/ai_validation/coordinator.py
maker/ai_validation/data_collector.py
maker/ai_validation/data_models.py
maker/ai_validation/decision_engine.py
maker/ai_validation/exceptions.py
maker/ai_validation/fallback_strategy.py
maker/ai_validation/logger.py
maker/ai_validation/monitor.py
maker/ai_validation/pattern_recognizer.py
maker/history_code/WickReversalStrategyMaker.py
maker/history_code/config.py
maker/history_code/okxapi.py
maker/history_code/zhen.py.bak
maker/history_code/zhen_2.py
maker/main.py
openfund_maker-2.5.50.dist-info/METADATA
openfund_maker-2.5.50.dist-info/WHEEL
openfund_maker-2.5.50.dist-info/entry_points.txt
openfund_maker-2.5.50.dist-info/RECORD
