Metadata-Version: 2.3
Name: openfund-maker
Version: 2.5.50
Summary: Openfund-maker.
Requires-Python: >=3.12,<4.0
Classifier: Programming Language :: Python :: 3
Classifier: Programming Language :: Python :: 3.12
Classifier: Programming Language :: Python :: 3.13
Requires-Dist: apscheduler (>=3.11.0,<4.0.0)
Requires-Dist: cachetools (>=5.3.2,<6.0.0)
Requires-Dist: ccxt (>=4.4.26,<5.0.0)
Requires-Dist: openfund-core (>=2.5.15,<3.0.0)
Requires-Dist: pandas (>=2.2.3,<3.0.0)
Requires-Dist: pyfiglet (>=1.0.2,<2.0.0)
Requires-Dist: python-dotenv (>=1.0.0,<2.0.0)
Requires-Dist: pyyaml (>=6.0.2,<7.0.0)
